xlsb2xlsx/__init__.py
xlsb2xlsx/__main__.py
xlsb2xlsx/xlsb2xlsx.py
xlsb2xlsx-0.1.dist-info/LICENSE
xlsb2xlsx-0.1.dist-info/METADATA
xlsb2xlsx-0.1.dist-info/WHEEL
xlsb2xlsx-0.1.dist-info/top_level.txt
xlsb2xlsx-0.1.dist-info/RECORD
