Metadata-Version: 2.1
Name: xlsb2xlsx
Version: 0.1
Summary: Convert .xlsb files to .xlsx.
Author: Brian Lewis
Requires-Python: >=3.7
License-File: LICENSE
